label_accelerator/__init__.py
label_accelerator/core.cp38-win_amd64.pyd
label_accelerator/core.cpp
label_accelerator/core.pyx
label_accelerator/core_py.py
label_accelerator/heuristics.py
label_accelerator/labeler.py
label_accelerator/license_validator.py
label_accelerator/models.py
label_accelerator_sdk-1.0.0.dist-info/METADATA
label_accelerator_sdk-1.0.0.dist-info/WHEEL
label_accelerator_sdk-1.0.0.dist-info/top_level.txt
label_accelerator_sdk-1.0.0.dist-info/RECORD
