Metadata-Version: 2.1
Name: label-accelerator-sdk
Version: 1.0.0
Summary: Accelerate AI development with programmatic data labeling and weak supervision.
Home-page: https://github.com/jaimeajl/label-accelerator
Author: Jaime Jimenez
Author-email: Jaime Jimenez <jaimeajl@hotmail.com>
License: MIT
Keywords: weak supervision,data labeling,programmatic labeling,mlops,ai,machine learning
Requires-Python: >=3.8
